README.md
setup.cfg
setup.py
ml_automation/__init__.py
ml_automation/package.py
ml_automation.egg-info/PKG-INFO
ml_automation.egg-info/SOURCES.txt
ml_automation.egg-info/dependency_links.txt
ml_automation.egg-info/requires.txt
ml_automation.egg-info/top_level.txt
ml_automation/factories/Factory.py
ml_automation/factories/__init__.py
ml_automation/metrics/__init__.py
ml_automation/metrics/accuracy.py
ml_automation/metrics/f1.py
ml_automation/metrics/precision.py
ml_automation/metrics/r2.py
ml_automation/metrics/recall.py
ml_automation/models/Model.py
ml_automation/models/__init__.py
ml_automation/models/classification/ClassificationModel.py
ml_automation/models/classification/LogisticRegression.py
ml_automation/models/classification/RandomForest.py
ml_automation/models/classification/XGBoost.py
ml_automation/models/classification/__init__.py
ml_automation/models/regression/RandomForest.py
ml_automation/models/regression/RegressionModel.py
ml_automation/models/regression/XGBoost.py
ml_automation/models/regression/__init__.py
ml_automation/preprocessing/Parser.py
ml_automation/preprocessing/Scaler.py
ml_automation/preprocessing/__init__.py
ml_automation/readers/__init__.py
ml_automation/readers/csv_reader.py
ml_automation/task_type/Task.py
ml_automation/task_type/__init__.py